ogc/__init__.py
ogc/actions.py
ogc/commands/__init__.py
ogc/commands/base.py
ogc/commands/db.py
ogc/commands/destroy.py
ogc/commands/init.py
ogc/commands/inspect.py
ogc/commands/launch.py
ogc/commands/list.py
ogc/commands/share.py
ogc/commands/ssh.py
ogc/commands/status.py
ogc/db.py
ogc/deployer.py
ogc/enums.py
ogc/exceptions.py
ogc/fs.py
ogc/log.py
ogc/provision.py
ogc/spec.py
ogc/state.py
ogc/tests/__init__.py
ogc-2.1.9.dist-info/entry_points.txt
ogc-2.1.9.dist-info/WHEEL
ogc-2.1.9.dist-info/METADATA
ogc-2.1.9.dist-info/RECORD
